{
    "title": "Adjective Order",
    "content": {
        "en": "# Order of Adjectives\n\nWhen we use multiple adjectives before a noun, they must follow a specific order.\n\n### The Royal Order (OSASCOMP)\n\n1.  **O**pinion: Beautiful, Ugly, Good\n2.  **S**ize: Big, Small, Tall\n3.  **A**ge: Old, Young, New\n4.  **S**hape: Round, Square\n5.  **C**olor: Red, Blue\n6.  **O**rigin: American, Chinese, Italian\n7.  **M**aterial: Plastic, Wooden, Silk\n8.  **P**urpose: Sleeping (bag), Running (shoes)\n\n### Examples\n\n*   *A **beautiful big old red** car.* (Opinion -> Size -> Age -> Color)\n*   *A **small square wooden** table.* (Size -> Shape -> Material)\n*   *An **expensive Italian leather** jacket.* (Opinion -> Origin -> Material)\n\n### Tip\n\nIt is rare to use more than 3 adjectives at once. If you do, it sounds unnatural!",
        "zh_TW": "# 形容詞順序\n\n當我們在名詞前使用多個形容詞時，必須遵守特定的順序。\n\n### 黃金順序 (OSASCOMP)\n\n1.  **O**pinion (觀點)：Beautiful (美), Ugly (醜), Good (好)\n2.  **S**ize (大小)：Big (大), Small (小)\n3.  **A**ge (年齡)：Old (舊), New (新)\n4.  **S**hape (形狀)：Round (圓), Square (方)\n5.  **C**olor (顏色)：Red (紅), Blue (藍)\n6.  **O**rigin (產地)：American (美國), Chinese (中式)\n7.  **M**aterial (材質)：Plastic (塑膠), Wooden (木製)\n8.  **P**urpose (用途)：Sleeping (睡-袋), Running (跑-鞋)\n\n### 範例\n\n*   *A **beautiful big old red** car.* (一台漂亮的大紅老爺車 - 觀點 -> 大小 -> 年齡 -> 顏色)\n*   *A **small square wooden** table.* (一張小方木桌 - 大小 -> 形狀 -> 材質)\n*   *An **expensive Italian leather** jacket.* (一件昂貴義大利皮夾克 - 觀點 -> 產地 -> 材質)\n\n### 小撇步\n\n很少同時使用超過 3 個形容詞。如果用的太多，聽起來會很不自然！",
        "zh_CN": "# 形容词顺序\n\n当我们在名词前使用多个形容词时，必须遵守特定的顺序。\n\n### 黄金顺序 (OSASCOMP)\n\n1.  **O**pinion (观点)：Beautiful (美), Ugly (丑), Good (好)\n2.  **S**ize (大小)：Big (大), Small (小)\n3.  **A**ge (年龄)：Old (旧), New (新)\n4.  **S**hape (形状)：Round (圆), Square (方)\n5.  **C**olor (颜色)：Red (红), Blue (蓝)\n6.  **O**rigin (产地)：American (美国), Chinese (中式)\n7.  **M**aterial (材质)：Plastic (塑料), Wooden (木制)\n8.  **P**urpose (用途)：Sleeping (睡-袋), Running (跑-鞋)\n\n### 范例\n\n*   *A **beautiful big old red** car.* (一台漂亮的大红老爷车 - 观点 -> 大小 -> 年龄 -> 颜色)\n*   *A **small square wooden** table.* (一张小方木桌 - 大小 -> 形状 -> 材质)\n*   *An **expensive Italian leather** jacket.* (一件昂贵意大利皮夹克 - 观点 -> 产地 -> 材质)\n\n### 小撇步\n\n很少同时使用超过 3 个形容词。如果用的太多，听起来会很不自然！"
    }
}